mer/__init__.py
mer/artifacts.py
mer/constants.py
mer/document_utils.py
mer/markdown.py
mer/mer.py
mer/model.py
mer/postprocess.py
mer/predictor.py
mer/surya.py
mer/types.py
mer/visualize.py
mer/vocab.py
mer-1.2.0.dist-info/licenses/LICENSE
mer-1.2.0.dist-info/METADATA
mer-1.2.0.dist-info/WHEEL
mer-1.2.0.dist-info/top_level.txt
mer-1.2.0.dist-info/RECORD
