Metadata-Version: 2.4
Name: mer
Version: 1.2.0
Summary: Khmer OCR
Home-page: https://github.com/MetythornPenn/mer.git
Author: Metythorn Penn
Author-email: metythorn@gmail.com
License: Apache Software License 2.0
Keywords: ocr
Classifier: Natural Language :: English
Classifier: License :: OSI Approved :: Apache Software License
Classifier: Operating System :: OS Independent
Classifier: Programming Language :: Python :: 3
License-File: LICENSE
Requires-Dist: torch
Requires-Dist: torchvision
Requires-Dist: onnxruntime-gpu
Requires-Dist: surya-ocr
Requires-Dist: pillow
Requires-Dist: huggingface-hub
Requires-Dist: tqdm
Dynamic: author
Dynamic: author-email
Dynamic: classifier
Dynamic: description
Dynamic: description-content-type
Dynamic: home-page
Dynamic: keywords
Dynamic: license
Dynamic: license-file
Dynamic: requires-dist
Dynamic: summary
